moonshot/__init__.py
moonshot/__main__.py
moonshot/api.py
moonshot/integrations/__init__.py
moonshot/integrations/cli/__init__.py
moonshot/integrations/cli/__main__.py
moonshot/integrations/cli/active_session_cfg.py
moonshot/integrations/cli/cli.py
moonshot/integrations/cli/cli_errors.py
moonshot/integrations/cli/benchmark/__init__.py
moonshot/integrations/cli/benchmark/benchmark.py
moonshot/integrations/cli/benchmark/cookbook.py
moonshot/integrations/cli/benchmark/datasets.py
moonshot/integrations/cli/benchmark/metrics.py
moonshot/integrations/cli/benchmark/recipe.py
moonshot/integrations/cli/benchmark/result.py
moonshot/integrations/cli/benchmark/run.py
moonshot/integrations/cli/benchmark/runner.py
moonshot/integrations/cli/common/__init__.py
moonshot/integrations/cli/common/common.py
moonshot/integrations/cli/common/connectors.py
moonshot/integrations/cli/common/dataset.py
moonshot/integrations/cli/common/display_helper.py
moonshot/integrations/cli/common/prompt_template.py
moonshot/integrations/cli/initialisation/__init__.py
moonshot/integrations/cli/initialisation/initialisation.py
moonshot/integrations/cli/redteam/__init__.py
moonshot/integrations/cli/redteam/attack_module.py
moonshot/integrations/cli/redteam/context_strategy.py
moonshot/integrations/cli/redteam/prompt_template.py
moonshot/integrations/cli/redteam/redteam.py
moonshot/integrations/cli/redteam/session.py
moonshot/integrations/cli/utils/process_data.py
moonshot/integrations/web_api/.env.dev
moonshot/integrations/web_api/__init__.py
moonshot/integrations/web_api/__main__.py
moonshot/integrations/web_api/app.py
moonshot/integrations/web_api/container.py
moonshot/integrations/web_api/logging_conf.py
moonshot/integrations/web_api/log/.gitkeep
moonshot/integrations/web_api/routes/__init__.py
moonshot/integrations/web_api/routes/attack_modules.py
moonshot/integrations/web_api/routes/benchmark.py
moonshot/integrations/web_api/routes/benchmark_result.py
moonshot/integrations/web_api/routes/bookmark.py
aiverify_moonshot-0.7.4.dist-info/METADATA
aiverify_moonshot-0.7.4.dist-info/WHEEL
aiverify_moonshot-0.7.4.dist-info/licenses/AUTHORS.md
aiverify_moonshot-0.7.4.dist-info/licenses/LICENSE.md
aiverify_moonshot-0.7.4.dist-info/licenses/NOTICES.md
aiverify_moonshot-0.7.4.dist-info/RECORD
