Metadata-Version: 2.4
Name: aiverify-moonshot
Version: 0.7.4
Summary: AI Verify advances Gen AI testing with Project Moonshot.
Project-URL: Repository, https://github.com/aiverify-foundation/moonshot
Project-URL: Documentation, https://aiverify-foundation.github.io/moonshot/
Project-URL: Issues, https://github.com/aiverify-foundation/moonshot/issues
Author-email: AI Verify Foundation <info@aiverify.sg>
License: Apache-2.0
License-File: AUTHORS.md
License-File: LICENSE.md
License-File: NOTICES.md
Classifier: Development Status :: 3 - Alpha
Classifier: License :: OSI Approved :: Apache Software License
Classifier: Programming Language :: Python :: 3
Classifier: Programming Language :: Python :: 3.11
Requires-Python: >=3.11
Requires-Dist: datasets~=3.2.0
Requires-Dist: ijson>=3.3.0
Requires-Dist: jinja2>=3.1.6
Requires-Dist: numpy~=1.26.4
Requires-Dist: pandas>=2.2.2
Requires-Dist: pydantic==2.8.2
Requires-Dist: pyparsing>=3.2.3
Requires-Dist: python-dotenv>=1.1.0
Requires-Dist: python-multipart>=0.0.9
Requires-Dist: python-slugify>=8.0.4
Requires-Dist: tenacity~=8.5.0
Requires-Dist: xxhash>=3.5.0
Provides-Extra: all
Requires-Dist: cmd2>=2.4.3; extra == 'all'
Requires-Dist: dependency-injector>=4.41.0; extra == 'all'
Requires-Dist: fastapi>=0.115.4; extra == 'all'
Requires-Dist: rich>=13.8.0; extra == 'all'
Requires-Dist: typing-extensions==4.13.2; extra == 'all'
Requires-Dist: uvicorn>=0.30.6; extra == 'all'
Provides-Extra: cli
Requires-Dist: cmd2>=2.4.3; extra == 'cli'
Requires-Dist: rich>=13.8.0; extra == 'cli'
Provides-Extra: web-api
Requires-Dist: dependency-injector>=4.41.0; extra == 'web-api'
Requires-Dist: fastapi>=0.115.4; extra == 'web-api'
Requires-Dist: typing-extensions==4.13.2; extra == 'web-api'
Requires-Dist: uvicorn>=0.30.6; extra == 'web-api'
